setup.py
python3_ctf/__init__.py
python3_ctf/main.py
python3_ctf.egg-info/PKG-INFO
python3_ctf.egg-info/SOURCES.txt
python3_ctf.egg-info/dependency_links.txt
python3_ctf.egg-info/requires.txt
python3_ctf.egg-info/top_level.txt