Metadata-Version: 2.1
Name: python3-ctf
Version: 1.0
Summary: desc
Home-page: UNKNOWN
Author: OsOmE1
Author-email: 
License: MIT
Download-URL: https://pypi.org/project/python3_ctf/
Keywords: simple_codecs,Encryption,Encoding
Platform: UNKNOWN
